weatherrouting/__init__.py
weatherrouting/grib.py
weatherrouting/polar.py
weatherrouting/routing.py
weatherrouting/utils.py
weatherrouting/routers/__init__.py
weatherrouting/routers/linearbestisorouter.py
weatherrouting/routers/router.py
weatherrouting/routers/shortestpathrouter.py
weatherrouting-0.2.3.dist-info/licenses/AUTHORS
weatherrouting-0.2.3.dist-info/licenses/LICENSE
weatherrouting-0.2.3.dist-info/METADATA
weatherrouting-0.2.3.dist-info/WHEEL
weatherrouting-0.2.3.dist-info/top_level.txt
weatherrouting-0.2.3.dist-info/RECORD
