Metadata-Version: 2.4
Name: weatherrouting
Version: 0.2.3
Summary: Weather routing library for sailing
Author: Davide Gessa
Author-email: gessadavide@gmail.com
License-File: LICENSE
License-File: AUTHORS
Requires-Dist: latlon3
Dynamic: author
Dynamic: author-email
Dynamic: license-file
Dynamic: requires-dist
Dynamic: summary
